digital_twin_tooling/__init__.py
digital_twin_tooling/__main__.py
digital_twin_tooling/amqp_data_repeater.py
digital_twin_tooling/basic.py
digital_twin_tooling/launchers.py
digital_twin_tooling/rabbitmq_fmu.py
digital_twin_tooling/tools.py
digital_twin_tooling/data/schema-0.0.1.yml
digital_twin_tooling/data/schema-0.0.2.yml
digital_twin_tooling-1.0.1.dist-info/LICENSE.txt
digital_twin_tooling-1.0.1.dist-info/METADATA
digital_twin_tooling-1.0.1.dist-info/WHEEL
digital_twin_tooling-1.0.1.dist-info/entry_points.txt
digital_twin_tooling-1.0.1.dist-info/top_level.txt
digital_twin_tooling-1.0.1.dist-info/RECORD
