Metadata-Version: 2.1
Name: digital-twin-tooling
Version: 1.0.1
Summary: A framework for working with digital twin systems and simulation
Home-page: https://github.com/INTO-CPS-Association/digital-twin-platform
Author: Kenneth Lausdahl
Author-email: kenneth@lausdahl.com
License: UNKNOWN
Project-URL: Bug Reports, https://github.com/INTO-CPS-Association/digital_twin_tooling/issues
Project-URL: Funding, https://github.com/INTO-CPS-Association/digital_twin_tooling
Project-URL: Source, https://github.com/INTO-CPS-Association/digital_twin_tooling.git
Keywords: digital twin,setuptools,development
Platform: UNKNOWN
Classifier: Development Status :: 3 - Alpha
Classifier: Intended Audience :: Developers
Classifier: Topic :: Software Development :: Build Tools
Classifier: License :: OSI Approved :: MIT License
Classifier: Programming Language :: Python :: 3
Classifier: Programming Language :: Python :: 3.6
Classifier: Programming Language :: Python :: 3.7
Classifier: Programming Language :: Python :: 3.8
Classifier: Programming Language :: Python :: 3.9
Classifier: Programming Language :: Python :: 3 :: Only
Requires-Python: >=3.9, <4
License-File: LICENSE.txt
Requires-Dist: jsonschema
Requires-Dist: pika
Requires-Dist: pyyaml
Requires-Dist: psutil
Requires-Dist: requests
Provides-Extra: dev
Requires-Dist: twine ; extra == 'dev'
Requires-Dist: pika-stubs ; extra == 'dev'
Requires-Dist: build ; extra == 'dev'
Provides-Extra: test
Requires-Dist: testcontainer-python-rabbitmq ; extra == 'test'
